<aetgt:getResponse xmlns:aetgt="http://schemas.active-endpoints.com/appmodules/repository/2010/10/avrepository.xsd"
                   xmlns:types1="http://schemas.active-endpoints.com/appmodules/repository/2010/10/avrepository.xsd">
   <types1:Item>
      <types1:EntryId>P274Rpf6JfOMWSw-gt-749200-2018-07-18T13:21:58.677Z::pd.xml</types1:EntryId>
      <types1:Name>execMultiSQLProxy</types1:Name>
      <types1:MimeType>application/xml+process</types1:MimeType>
      <types1:Description>This service allows to Access the execMultiSQL DAS Services running on the Secure Agent from the cloud process or the guide.</types1:Description>
      <types1:AppliesTo/>
      <types1:Tags>.agent:iclab</types1:Tags>
      <types1:VersionLabel>1.0</types1:VersionLabel>
      <types1:State>CURRENT</types1:State>
      <types1:ProcessGroup/>
      <types1:CreatedBy>jbrazda-iics@informatica.com</types1:CreatedBy>
      <types1:CreationDate>2018-07-18T13:21:59Z</types1:CreationDate>
      <types1:ModifiedBy>jbrazda-iics@informatica.com</types1:ModifiedBy>
      <types1:ModificationDate>2018-10-15T13:55:11Z</types1:ModificationDate>
      <types1:PublicationStatus>published</types1:PublicationStatus>
      <types1:PublishedBy>jbrazda-iics@informatica.com</types1:PublishedBy>
      <types1:PublicationDate>2019-11-05T19:20:03Z</types1:PublicationDate>
      <types1:PublishedContributionId>project:/spi.execMultiSQLProxy/execMultiSQLProxy.pd.xml</types1:PublishedContributionId>
      <types1:AutosaveExists>false</types1:AutosaveExists>
      <types1:Entry>
         <process xmlns="http://schemas.active-endpoints.com/appmodules/screenflow/2010/10/avosScreenflow.xsd"
                  xmlns:list="urn:activevos:spi:list:functions"
                  displayName="execMultiSQLProxy"
                  name="execMultiSQLProxy">
            <appliesTo/>
            <description>This service allows to Access the execMultiSQL DAS Services running on the Secure Agent from the cloud process or the guide.</description>
            <tags>.agent:iclab</tags>
            <generator>Informatica Process Designer 9</generator>
            <input>
               <parameter description="" name="multiDataAccessrequest" type="reference">
                  <options>
                     <option name="referenceTo">DataAccessService:tMultiDataAccessRequest</option>
                     <option name="required">false</option>
                     <option name="isCopy">true</option>
                  </options>
               </parameter>
            </input>
            <output>
               <field description="" name="multiDataAccessResponse" type="string">
                  <options>
                     <option name="required">false</option>
                  </options>
               </field>
            </output>
            <notes/>
            <deployment suspendOnFault="false" tracingLevel="none">
               <targetLocation>iclab</targetLocation>
               <rest/>
            </deployment>
            <flow id="a">
               <start id="b">
                  <link id="link1" targetId="ivijk40j"/>
               </start>
               <eventContainer id="ivijk40j">
                  <service id="c">
                     <title>execMultiSQL</title>
                     <serviceName>execMultiSQL</serviceName>
                     <serviceGUID/>
                     <serviceInput>
                        <parameter name="multiDataAccessRequest" source="field">input.multiDataAccessrequest</parameter>
                     </serviceInput>
                  </service>
                  <flow id="ivijk40m">
                     <assignment id="ivijuo3u">
                        <title>Assignment to multiDataAccessResponse</title>
                        <operation source="field" to="output.multiDataAccessResponse">output.multiDataAccessResponse</operation>
                     </assignment>
                     <link id="ivijk40n" targetId="ivijk40j" type="containerLink"/>
                  </flow>
                  <flow id="ivijk40q">
                     <throw id="ivijsoca">
                        <title>Untitled</title>
                        <throwInput>
                           <parameter name="code" source="field" updatable="true">output.faultInfo[1]/code</parameter>
                           <parameter name="detail" source="field" updatable="true">output.faultInfo[1]/detail</parameter>
                           <parameter name="reason" source="field" updatable="true">output.faultInfo[1]/reason</parameter>
                        </throwInput>
                     </throw>
                  </flow>
                  <link id="ivijk40k" targetId="ivijk40m" type="containerLink"/>
                  <link id="ivijuo3x" targetId="d"/>
                  <events>
                     <catch faultField="faultInfo" id="ivijk40f" interrupting="true">
                        <link id="ivijk40o" targetId="ivijk40q" type="containerLink"/>
                     </catch>
                  </events>
               </eventContainer>
               <end id="d"/>
            </flow>
         </process>
      </types1:Entry>
      <types1:GUID>1H3UtktK7r4hpKFkSq0gYT</types1:GUID>
      <types1:DisplayName>execMultiSQLProxy</types1:DisplayName>
   </types1:Item>
   <types1:CurrentServerDateTime>2020-03-23T18:48:03.702Z</types1:CurrentServerDateTime>
</aetgt:getResponse>
