[
   {
      "objectGuid": "8WPWXuoACwji7tDXMjdfg2",
      "objectName": "IPaaS Administration Tools",
      "objectType": "GUIDE",
      "path": "/Explore/Tools/Guides",
      "metadata": {
         "additionalInfo": {
            "contentType": "application/json; charset=utf-8",
            "description": "IIICS Custom Administration Tools Launcher \nversion: 1.6",
            "documentState": "VALID"
         },
         "contextAttributes": null,
         "modelVersion": {
            "major": 1,
            "minor": 0
         },
         "objectRefs": [
            "0FCslbR0FsshCmxMcjULOJ",
            "aqpUO15ISL4jLLs0xDJxmL",
            "1iZssfMiHihflxy0AoH4Il",
            "3mpz03dfst4hjYMSmmgXes",
            "i2sGIbd2BUUkea7gdkm785"
         ],
         "repoInfo": {
            "repoHandle": "lm34jBvSx0aa-gt-5281442-2020-03-24T18:08:21.78Z::gt.xml"
         }
      }
   },
   {
      "objectGuid": "0FCslbR0FsshCmxMcjULOJ",
      "objectName": "iPaaS Admin Upload File to Agent",
      "objectType": "GUIDE",
      "path": "/Explore/Tools/Guides",
      "metadata": {
         "additionalInfo": {
            "contentType": "application/json; charset=utf-8",
            "description": "Utility Guide to Upload File to Secure Agent\nversion: 1.6",
            "documentState": "VALID"
         },
         "contextAttributes": null,
         "modelVersion": {
            "major": 1,
            "minor": 0
         },
         "objectRefs": [],
         "repoInfo": {
            "repoHandle": "RrHY2KsJlv58pIO-gt-5237599-2020-03-24T18:08:18.694Z::gt.xml"
         }
      }
   },
   {
      "objectGuid": "aqpUO15ISL4jLLs0xDJxmL",
      "objectName": "Admin Shell",
      "objectType": "GUIDE",
      "path": "/Explore/Tools/Guides",
      "metadata": {
         "additionalInfo": {
            "contentType": "application/json; charset=utf-8",
            "description": "Utility Guide to Invoke Shell commands on the  Secure Agent \nversion: 1.6",
            "documentState": "VALID"
         },
         "contextAttributes": null,
         "modelVersion": {
            "major": 1,
            "minor": 0
         },
         "objectRefs": [],
         "repoInfo": {
            "repoHandle": "sFEkWoKeERhKGXS-gt-1951763-2020-03-24T18:08:17.291Z::gt.xml"
         }
      }
   },
   {
      "objectGuid": "1iZssfMiHihflxy0AoH4Il",
      "objectName": "Conversion Utility",
      "objectType": "GUIDE",
      "path": "/Explore/Tools/Guides",
      "metadata": {
         "additionalInfo": {
            "contentType": "application/json; charset=utf-8",
            "description": "Guide to convert XML sample data to JSON and vice versa.\nversion: 1.6",
            "documentState": "VALID"
         },
         "contextAttributes": null,
         "modelVersion": {
            "major": 1,
            "minor": 0
         },
         "objectRefs": [],
         "repoInfo": {
            "repoHandle": "8RVf4VQT53nQciS-gt-5306339-2020-03-24T18:08:11.962Z::gt.xml"
         }
      }
   },
   {
      "objectGuid": "3mpz03dfst4hjYMSmmgXes",
      "objectName": "iPaaS Log Search SFDC",
      "objectType": "GUIDE",
      "path": "/Explore/Logging/Guides_SFDC",
      "metadata": {
         "additionalInfo": {
            "contentType": "application/json; charset=utf-8",
            "description": "This Guide  Provides Administrative and troubleshooting functions such as \n- Search IPaaS  ICRT Job  logs\n- ability to find job related processes",
            "documentState": "VALID"
         },
         "contextAttributes": null,
         "modelVersion": {
            "major": 1,
            "minor": 0
         },
         "objectRefs": [],
         "repoInfo": {
            "repoHandle": "zCZcjKsJlv58pIO-gt-5281377-2020-03-24T18:08:19.405Z::gt.xml"
         }
      }
   },
   {
      "objectGuid": "i2sGIbd2BUUkea7gdkm785",
      "objectName": "IPaaS Encrypt Utility",
      "objectType": "GUIDE",
      "path": "/Explore/Tools/Guides",
      "metadata": {
         "additionalInfo": {
            "contentType": "application/json; charset=utf-8",
            "description": "Utility To encrypt Strings for configuration to be used in Automated steps\nversion: 1.6",
            "documentState": "VALID"
         },
         "contextAttributes": null,
         "modelVersion": {
            "major": 1,
            "minor": 0
         },
         "objectRefs": [],
         "repoInfo": {
            "repoHandle": "Ki0lHww43dtQR6k-gt-5306430-2020-03-24T18:08:15.92Z::gt.xml"
         }
      }
   }
]
