[
   {
      "objectGuid": "1R7HR8lHtqokk5PjBqd5Ot",
      "objectName": "TEMPLATE-MP-Job-DAS",
      "objectType": "PROCESS",
      "path": "/Explore/Templates/Jobs-Logging-CAI",
      "metadata": {
         "additionalInfo": {
            "contentType": "application/json; charset=utf-8",
            "description": "Template for Main Job Processes\nversion: 1.6",
            "documentState": "VALID"
         },
         "contextAttributes": null,
         "modelVersion": {
            "major": 1,
            "minor": 0
         },
         "objectRefs": [
            "2QfZeXrDYnxllsH2E5Ln0p",
            "26cL6twFPqoexROE7JNxGL",
            "3QG2CiWOVAxfRHE6bp5cmb"
         ],
         "repoInfo": {
            "repoHandle": "u8QhxOSM8NciZBp-gt-38704198-2024-01-09T22:16:21.331Z::pd.xml"
         }
      }
   },
   {
      "objectGuid": "2QfZeXrDYnxllsH2E5Ln0p",
      "objectName": "ProcessExecutionContext",
      "objectType": "PROCESS_OBJECT",
      "path": "/Explore/Logging/ProcessObjects",
      "metadata": {
         "additionalInfo": {
            "contentType": "application/json; charset=utf-8",
            "description": "This Process Object should be used to pass down context information to the child execution process when they are called from a parent process or keep a status information version: 2.0",
            "documentState": "VALID"
         },
         "contextAttributes": null,
         "modelVersion": {
            "major": 1,
            "minor": 0
         },
         "objectRefs": [],
         "repoInfo": {
            "repoHandle": "txcnfXjISUXL86z-gt-38662849-2024-01-09T22:16:14.322Z::po.xml"
         }
      }
   },
   {
      "objectGuid": "26cL6twFPqoexROE7JNxGL",
      "objectName": "CreateJobLogEventRequest",
      "objectType": "PROCESS_OBJECT",
      "path": "/Explore/Logging/ProcessObjects",
      "metadata": {
         "additionalInfo": {
            "contentType": "application/json; charset=utf-8",
            "description": "IPaaS Job Log Event",
            "documentState": "VALID"
         },
         "contextAttributes": null,
         "modelVersion": {
            "major": 1,
            "minor": 0
         },
         "objectRefs": [],
         "repoInfo": {
            "repoHandle": "slEt5OjiTIKchzt-gt-38663106-2024-01-09T22:16:19.303Z::po.xml"
         }
      }
   },
   {
      "objectGuid": "3QG2CiWOVAxfRHE6bp5cmb",
      "objectName": "TEMPLATE-SP-ETL-DAS",
      "objectType": "PROCESS",
      "path": "/Explore/Templates/Jobs-Logging-CAI",
      "metadata": {
         "additionalInfo": {
            "contentType": "application/json; charset=utf-8",
            "description": "Template for Integration Sub-Process (SP) Demo\nversion: 1.6",
            "documentState": "VALID"
         },
         "contextAttributes": null,
         "modelVersion": {
            "major": 1,
            "minor": 0
         },
         "objectRefs": [],
         "repoInfo": {
            "repoHandle": "3GVUDv2vSx0aa-gt-38743350-2024-01-09T22:16:13.886Z::pd.xml"
         }
      }
   }
]
